azure/mgmt/kubernetesconfiguration/fluxconfigurations/__init__.py
azure/mgmt/kubernetesconfiguration/fluxconfigurations/_configuration.py
azure/mgmt/kubernetesconfiguration/fluxconfigurations/_kubernetes_configuration_flux_configurations_mgmt_client.py
azure/mgmt/kubernetesconfiguration/fluxconfigurations/_patch.py
azure/mgmt/kubernetesconfiguration/fluxconfigurations/_version.py
azure/mgmt/kubernetesconfiguration/fluxconfigurations/py.typed
azure/mgmt/kubernetesconfiguration/fluxconfigurations/_utils/__init__.py
azure/mgmt/kubernetesconfiguration/fluxconfigurations/_utils/serialization.py
azure/mgmt/kubernetesconfiguration/fluxconfigurations/aio/__init__.py
azure/mgmt/kubernetesconfiguration/fluxconfigurations/aio/_configuration.py
azure/mgmt/kubernetesconfiguration/fluxconfigurations/aio/_kubernetes_configuration_flux_configurations_mgmt_client.py
azure/mgmt/kubernetesconfiguration/fluxconfigurations/aio/_patch.py
azure/mgmt/kubernetesconfiguration/fluxconfigurations/aio/operations/__init__.py
azure/mgmt/kubernetesconfiguration/fluxconfigurations/aio/operations/_flux_config_operation_status_operations.py
azure/mgmt/kubernetesconfiguration/fluxconfigurations/aio/operations/_flux_configurations_operations.py
azure/mgmt/kubernetesconfiguration/fluxconfigurations/aio/operations/_patch.py
azure/mgmt/kubernetesconfiguration/fluxconfigurations/models/__init__.py
azure/mgmt/kubernetesconfiguration/fluxconfigurations/models/_kubernetes_configuration_flux_configurations_mgmt_client_enums.py
azure/mgmt/kubernetesconfiguration/fluxconfigurations/models/_models_py3.py
azure/mgmt/kubernetesconfiguration/fluxconfigurations/models/_patch.py
azure/mgmt/kubernetesconfiguration/fluxconfigurations/operations/__init__.py
azure/mgmt/kubernetesconfiguration/fluxconfigurations/operations/_flux_config_operation_status_operations.py
azure/mgmt/kubernetesconfiguration/fluxconfigurations/operations/_flux_configurations_operations.py
azure_mgmt_kubernetesconfiguration_fluxconfigurations-1.0.0b1.dist-info/LICENSE
azure_mgmt_kubernetesconfiguration_fluxconfigurations-1.0.0b1.dist-info/METADATA
azure_mgmt_kubernetesconfiguration_fluxconfigurations-1.0.0b1.dist-info/WHEEL
azure_mgmt_kubernetesconfiguration_fluxconfigurations-1.0.0b1.dist-info/top_level.txt
azure_mgmt_kubernetesconfiguration_fluxconfigurations-1.0.0b1.dist-info/RECORD
